simple_asgi/__init__.py
simple_asgi/app.py
simple_asgi/body.py
simple_asgi/connection.py
simple_asgi/exceptions.py
simple_asgi/request.py
simple_asgi/response.py
simple_asgi/router.py
simple_asgi/runner.py
simple_asgi/tests/__init__.py
simple_asgi/tests/test_router.py
simple_asgi-0.0.2.dist-info/AUTHORS
simple_asgi-0.0.2.dist-info/LICENSE
simple_asgi-0.0.2.dist-info/METADATA
simple_asgi-0.0.2.dist-info/WHEEL
simple_asgi-0.0.2.dist-info/pbr.json
simple_asgi-0.0.2.dist-info/top_level.txt
simple_asgi-0.0.2.dist-info/RECORD
