Metadata-Version: 2.1
Name: simple-asgi
Version: 0.0.2
Summary: Simple ASGI HTTP 1.1 web server
Home-page: https://github.com/denismakogon
Author: Denis Makogon
Author-email: denys.makogon@oracle.com
License: UNKNOWN
Platform: UNKNOWN
Classifier: Intended Audience :: Information Technology
Classifier: Intended Audience :: System Administrators
Classifier: License :: OSI Approved :: Apache Software License
Classifier: Operating System :: POSIX :: Linux
Classifier: Programming Language :: Python
Classifier: Programming Language :: Python :: 3
Classifier: Programming Language :: Python :: 3.7
Requires-Dist: pbr (!=2.1.0,>=2.0.0)
Requires-Dist: hypercorn (==0.4.6)
Requires-Dist: multidict (==4.5.2)
